vmbox/__init__.py
vmbox/cloud_images.py
vmbox/repositories.yaml
vmbox/vmbox.py
vmbox-0.1.1.dist-info/LICENSE
vmbox-0.1.1.dist-info/METADATA
vmbox-0.1.1.dist-info/WHEEL
vmbox-0.1.1.dist-info/entry_points.txt
vmbox-0.1.1.dist-info/top_level.txt
vmbox-0.1.1.dist-info/RECORD
