Metadata-Version: 2.1
Name: vmbox
Version: 0.1.1
Summary: Manage Virtual Machines with Cloud Images
Home-page: https://gitlab.com/digitronik/miqbox
Author: Nikhil Dhandre
Author-email: nik.digitronik@live.com
License: GPLv2
Keywords: vmbox
Platform: any
Classifier: Development Status :: 1 - Planning
Classifier: Environment :: Console
Classifier: Natural Language :: English
Classifier: Programming Language :: Python :: 3
Requires-Dist: bs4 (>=0.0.1)
Requires-Dist: Click (>=5.0)
Requires-Dist: libvirt-python (>=4.0)
Requires-Dist: requests (>=2.20)
Requires-Dist: ruamel.yaml (~=0.15)
